constrainedfilefield/__init__.py
constrainedfilefield/fields/__init__.py
constrainedfilefield/fields/file.py
constrainedfilefield/fields/image.py
constrainedfilefield/locale/en/LC_MESSAGES/django.mo
constrainedfilefield/locale/en/LC_MESSAGES/django.po
constrainedfilefield/locale/es/LC_MESSAGES/django.mo
constrainedfilefield/locale/es/LC_MESSAGES/django.po
constrainedfilefield/locale/fr/LC_MESSAGES/django.po
constrainedfilefield/static/constrainedfilefield/js/file_checker.js
constrainedfilefield/tests/__init__.py
constrainedfilefield/tests/__main__.py
constrainedfilefield/tests/forms.py
constrainedfilefield/tests/models.py
constrainedfilefield/tests/settings.py
constrainedfilefield/tests/urls.py
constrainedfilefield/tests/views.py
constrainedfilefield/tests/tests/__init__.py
constrainedfilefield/tests/tests/backend.py
constrainedfilefield/tests/tests/frontend.py
django_constrainedfilefield-5.0.0.dist-info/LICENSE
django_constrainedfilefield-5.0.0.dist-info/METADATA
django_constrainedfilefield-5.0.0.dist-info/WHEEL
django_constrainedfilefield-5.0.0.dist-info/top_level.txt
django_constrainedfilefield-5.0.0.dist-info/RECORD
