Metadata-Version: 2.1
Name: django-constrainedfilefield
Version: 5.0.0
Summary: This Django app adds a new field type, ConstrainedFileField, that has the capability of checking the document size and type.
Home-page: https://github.com/mbourqui/django-constrainedfilefield/
Author: Marc Bourqui
Author-email: pypi.kemar@bourqui.org
License: BSD
Download-URL: https://github.com/mbourqui/django-constrainedfilefield/releases/tag/v5.0.0
Keywords: django filefield validation file
Platform: UNKNOWN
Classifier: Development Status :: 5 - Production/Stable
Classifier: Environment :: Web Environment
Classifier: Framework :: Django
Classifier: Framework :: Django :: 1.11
Classifier: Framework :: Django :: 2.1
Classifier: Framework :: Django :: 2.2
Classifier: Intended Audience :: Developers
Classifier: License :: OSI Approved :: BSD License
Classifier: Operating System :: OS Independent
Classifier: Programming Language :: Python
Classifier: Programming Language :: Python :: 3
Classifier: Programming Language :: Python :: 3.5
Classifier: Programming Language :: Python :: 3.6
Classifier: Programming Language :: Python :: 3.7
Classifier: Programming Language :: Python :: 3.8
Classifier: Topic :: Internet :: WWW/HTTP
Classifier: Topic :: Internet :: WWW/HTTP :: Dynamic Content
Classifier: Topic :: Utilities
License-File: LICENSE
Requires-Dist: django (>=1.11) ; python_version >= "3.5"
Provides-Extra: coverage
Requires-Dist: Pillow (>=4.0.0) ; extra == 'coverage'
Requires-Dist: python-magic (>=0.4.2) ; (platform_system != "Windows") and extra == 'coverage'
Requires-Dist: python-magic-bin ; (platform_system == "Windows") and extra == 'coverage'
Provides-Extra: filetype
Requires-Dist: python-magic (>=0.4.2) ; (platform_system != "Windows") and extra == 'filetype'
Requires-Dist: python-magic-bin ; (platform_system == "Windows") and extra == 'filetype'
Provides-Extra: image
Requires-Dist: Pillow (>=4.0.0) ; extra == 'image'
